.gitignore
LICENSE
README.md
setup.cfg
setup.py
examples/bare_example.py
examples/bare_np_example.py
examples/ez_example.py
examples/ez_hs071.py
mseipopt/__init__.py
mseipopt/bare.py
mseipopt/bare_np.py
mseipopt/ez.py
mseipopt.egg-info/PKG-INFO
mseipopt.egg-info/SOURCES.txt
mseipopt.egg-info/dependency_links.txt
mseipopt.egg-info/top_level.txt
mseipopt/tests/test_ez.py