Metadata-Version: 2.1
Name: mseipopt
Version: 0.1.dev1
Summary: The most simple ever python IPOPT interface.
Home-page: http://github.com/cea-ufmg/mseipopt
Author: Dimas Abreu Archanjo Dutra
Author-email: dimasad@ufmg.br
License: MIT
Platform: Windows
Platform: Linux
Platform: Solaris
Platform: Mac OS-X
Platform: Unix
Classifier: Intended Audience :: Developers
Classifier: Intended Audience :: Science/Research
Classifier: License :: OSI Approved
Classifier: License :: OSI Approved :: MIT License
Classifier: Operating System :: MacOS
Classifier: Operating System :: Microsoft :: Windows
Classifier: Operating System :: POSIX
Classifier: Operating System :: Unix
Classifier: Programming Language :: Python
Classifier: Programming Language :: Python :: 3
Classifier: Topic :: Scientific/Engineering
Classifier: Topic :: Software Development
